bertforyou
example
