Metadata-Version: 1.1
Name: bertforyou
Version: 1.1.8
Summary: a package for your bert using
Home-page: https://github.com/boss2020/tfbert
Author: xiaoguzai
Author-email: 474551240@qq.com
License: Apache License 2.0
Download-URL: https://github.com/boss2020/tfbert/master.zip
Platform: UNKNOWN
